[
    {
        "LAST_SWITCHED": 384100,
        "FIRST_SWITCHED": 382028,
        "IN_BYTES": 252,
        "IN_PKTS": 3,
        "INPUT_SNMP": 28,
        "OUTPUT_SNMP": 6,
        "IPV4_SRC_ADDR": "192.168.1.2",
        "IPV4_DST_ADDR": "216.58.193.46",
        "PROTOCOL": 1,
        "SRC_TOS": 0,
        "L4_SRC_PORT": 0,
        "L4_DST_PORT": 2048,
        "FLOW_SAMPLER_ID": 0,
        "UNKNOWN_FIELD_TYPE": 0,
        "IPV4_NEXT_HOP": 3232253185,
        "DST_MASK": 0,
        "SRC_MASK": 24,
        "TCP_FLAGS": 16,
        "DIRECTION": 0,
        "DST_AS": 0,
        "SRC_AS": 0
    },
    {
        "LAST_SWITCHED": 384168,
        "FIRST_SWITCHED": 382096,
        "IN_BYTES": 252,
        "IN_PKTS": 3,
        "INPUT_SNMP": 6,
        "OUTPUT_SNMP": 28,
        "IPV4_SRC_ADDR": "216.58.193.46",
        "IPV4_DST_ADDR": "192.168.1.2",
        "PROTOCOL": 1,
        "SRC_TOS": 0,
        "L4_SRC_PORT": 0,
        "L4_DST_PORT": 0,
        "FLOW_SAMPLER_ID": 0,
        "UNKNOWN_FIELD_TYPE": 0,
        "IPV4_NEXT_HOP": 3232235778,
        "DST_MASK": 24,
        "SRC_MASK": 0,
        "TCP_FLAGS": 16,
        "DIRECTION": 1,
        "DST_AS": 0,
        "SRC_AS": 0
    },
    {
        "LAST_SWITCHED": 388272,
        "FIRST_SWITCHED": 388272,
        "IN_BYTES": 56,
        "IN_PKTS": 1,
        "INPUT_SNMP": 28,
        "OUTPUT_SNMP": 0,
        "IPV4_SRC_ADDR": "192.168.1.2",
        "IPV4_DST_ADDR": "8.8.8.8",
        "PROTOCOL": 17,
        "SRC_TOS": 0,
        "L4_SRC_PORT": 20816,
        "L4_DST_PORT": 53,
        "FLOW_SAMPLER_ID": 0,
        "UNKNOWN_FIELD_TYPE": 0,
        "IPV4_NEXT_HOP": 3232253185,
        "DST_MASK": 0,
        "SRC_MASK": 24,
        "TCP_FLAGS": 16,
        "DIRECTION": 0,
        "DST_AS": 0,
        "SRC_AS": 0
    }
]